LICENSE
README.rst
setup.py
cephclient/__init__.py
cephclient/client.py
cephclient/exceptions.py
cephclient/wrapper.py
python_cephclient.egg-info/PKG-INFO
python_cephclient.egg-info/SOURCES.txt
python_cephclient.egg-info/dependency_links.txt
python_cephclient.egg-info/requires.txt
python_cephclient.egg-info/top_level.txt