Metadata-Version: 1.1
Name: python-cephclient
Version: 0.1.0.4
Summary: A client library in python for the Ceph REST API.
Home-page: https://github.com/dmsimard/python-cephclient
Author: David Moreau Simard
Author-email: moi@dmsimard.com
License: Apache License, Version 2.0
Keywords: ceph rest api ceph-rest-api client library
Platform: UNKNOWN
Classifier: License :: OSI Approved :: Apache Software License
Classifier: Development Status :: 3 - Alpha
Classifier: Intended Audience :: Developers
Classifier: Intended Audience :: System Administrators
Classifier: Intended Audience :: Information Technology
Classifier: Programming Language :: Python :: 2.7
Classifier: Topic :: Utilities
